shapefile2db/__init__.py
shapefile2db/cli.py
shapefile2db/core.py
shapefile2db/shape_file_exporter.py
shapefile2db/state_shape_file_exporter.py
shapefile2db/address_db/__init__.py
shapefile2db/address_db/address_constants.py
shapefile2db/address_db/address_database.py
shapefile2db/address_db/address_models.py
shapefile2db/address_db/temp.txt
shapefile2db/assets/ShapeFile2DB_logo.png
shapefile2db/assets/ShapeFile2DB_output.gif
shapefile2db/assets/output_1.png
shapefile2db-0.1.8.dist-info/METADATA
shapefile2db-0.1.8.dist-info/WHEEL
shapefile2db-0.1.8.dist-info/entry_points.txt
shapefile2db-0.1.8.dist-info/RECORD
