Metadata-Version: 2.4
Name: shapefile2db
Version: 0.1.8
Summary: Exports US Census ZCTA (Zip Code Tabulation Area) shapefiles to a SQLite database via CLI or Python API.
Project-URL: Homepage, https://github.com/rlapine/shapefile2db
Project-URL: Documentation, https://github.com/rlapine/shapefile2db/blob/624aa335a27f6db7b56f53907ff8aecf3f031ba7/README.md
Project-URL: Repository, https://github.com/rlapine/shapefile2db
Author-email: Ryan Lapine <github.stunt845@passinbox.com>
Maintainer-email: Ryan Lapine <github.stunt845@passinbox.com>
License: MIT
Keywords: SQLite,ZCTA,census data,data export,geodata,geospatial,shapefile,spatial database,vector data
Classifier: Intended Audience :: Developers
Classifier: Intended Audience :: Information Technology
Classifier: Intended Audience :: Science/Research
Classifier: License :: OSI Approved :: MIT License
Classifier: Operating System :: OS Independent
Classifier: Programming Language :: Python :: 3
Classifier: Programming Language :: Python :: 3.8
Classifier: Programming Language :: Python :: 3.9
Classifier: Programming Language :: Python :: 3.10
Classifier: Programming Language :: Python :: 3.11
Classifier: Topic :: Scientific/Engineering :: GIS
Classifier: Topic :: Scientific/Engineering :: Information Analysis
Classifier: Topic :: Software Development :: Libraries
Classifier: Topic :: Utilities
Requires-Python: >=3.8
Requires-Dist: geopandas==1.1.1
Requires-Dist: pandas==2.3.2
Requires-Dist: printpop==0.2.2
Requires-Dist: pyogrio==0.11.0
Requires-Dist: setuptools==80.9.0
Requires-Dist: shapely==2.1.1
Requires-Dist: sqlalchemy==2.0.43
